CHANGES.txt
CONTRIBUTORS.txt
MANIFEST.in
README.txt
setup.cfg
setup.py
docs/HISTORY.txt
docs/INSTALL.txt
docs/LICENSE.GPL
docs/LICENSE.txt
zettwerk/__init__.py
zettwerk.mailtemplates.egg-info/PKG-INFO
zettwerk.mailtemplates.egg-info/SOURCES.txt
zettwerk.mailtemplates.egg-info/dependency_links.txt
zettwerk.mailtemplates.egg-info/entry_points.txt
zettwerk.mailtemplates.egg-info/namespace_packages.txt
zettwerk.mailtemplates.egg-info/not-zip-safe
zettwerk.mailtemplates.egg-info/paster_plugins.txt
zettwerk.mailtemplates.egg-info/requires.txt
zettwerk.mailtemplates.egg-info/top_level.txt
zettwerk/mailtemplates/README.txt
zettwerk/mailtemplates/__init__.py
zettwerk/mailtemplates/config.py
zettwerk/mailtemplates/configure.zcml
zettwerk/mailtemplates/setuphandler.py
zettwerk/mailtemplates/z.png
zettwerk/mailtemplates/Extensions/Install.py
zettwerk/mailtemplates/browser/__init__.py
zettwerk/mailtemplates/browser/configure.zcml
zettwerk/mailtemplates/browser/mail_template_toolview.pt
zettwerk/mailtemplates/browser/mail_template_toolview.py
zettwerk/mailtemplates/browser/send_emailview.py
zettwerk/mailtemplates/browser/simulateview.py
zettwerk/mailtemplates/browser/templateview.pt
zettwerk/mailtemplates/browser/templateview.py
zettwerk/mailtemplates/browser/unprotectedrendered.py
zettwerk/mailtemplates/content/__init__.py
zettwerk/mailtemplates/content/configure.zcml
zettwerk/mailtemplates/content/mailtemplatetool.py
zettwerk/mailtemplates/content/template.py
zettwerk/mailtemplates/filters/__init__.py
zettwerk/mailtemplates/filters/reminder.py
zettwerk/mailtemplates/interfaces/__init__.py
zettwerk/mailtemplates/interfaces/mailtemplatetool.py
zettwerk/mailtemplates/interfaces/template.py
zettwerk/mailtemplates/locales/zettwerk.mailtemplates.pot
zettwerk/mailtemplates/locales/de/LC_MESSAGES/zettwerk.mailtemplates.mo
zettwerk/mailtemplates/locales/de/LC_MESSAGES/zettwerk.mailtemplates.po
zettwerk/mailtemplates/portlets/__init__.py
zettwerk/mailtemplates/portlets/configure.zcml
zettwerk/mailtemplates/profiles/default/controlpanel.xml
zettwerk/mailtemplates/profiles/default/factorytool.xml
zettwerk/mailtemplates/profiles/default/metadata.xml
zettwerk/mailtemplates/profiles/default/portlets.xml
zettwerk/mailtemplates/profiles/default/rolemap.xml
zettwerk/mailtemplates/profiles/default/toolset.xml
zettwerk/mailtemplates/profiles/default/types.xml
