Metadata-Version: 1.1
Name: zettwerk.mailtemplates
Version: 0.2
Summary: Create and send mail templates in plone.
Home-page: http://zettwerk.com
Author: Jörg Kubaile / zettwerk GmbH
Author-email: jk@zettwerk.com
License: GPL
Keywords: Plone
Platform: UNKNOWN
Classifier: Framework :: Plone
Classifier: Intended Audience :: Developers
Classifier: License :: OSI Approved :: GNU General Public License (GPL)
